taska/__init__.py
taska/__main__.py
taska/config.py
taska/core.py
taska/bottle_app/__main__.py
taska/bottle_app/app.py
taska/bottle_app/console_template.py
taska/templates/runner.py
taska-0.1.7.dist-info/LICENSE
taska-0.1.7.dist-info/WHEEL
taska-0.1.7.dist-info/METADATA
taska-0.1.7.dist-info/RECORD
