Metadata-Version: 2.1
Name: taska
Version: 0.1.7
Summary: Taska is a web console for running python code
Author-email: ClericPy <clericpy@gmail.com>
Requires-Python: >=3.7
Classifier: License :: OSI Approved :: MIT License
Requires-Dist: morebuiltins >=1.0.9
Requires-Dist: bottle
Requires-Dist: waitress
Requires-Dist: psutil
Project-URL: Home, https://github.com/ClericPy/taska
